rtl/mux4to1_32bit.v
module mux4to1_32bit (input [31:0] a, b, c, d, input [1:0] sel, output [31:0] out);
    assign out = (sel == 2'b00) ? a :
                    (sel == 2'b01) ? b :
                    (sel == 2'b10) ? c :
                    d;
endmodule

tb/tb_mux4to1_32bit.v
module tb_mux4to1_32bit;
    reg [31:0] a, b, c, d;
    reg [1:0] sel;
    wire [31:0] out;

    mux4to1_32bit uut (.a(a), .b(b), .c(c), .d(d), .sel(sel), .out(out));

    reg [31:0] expected;
    integer error_count = 0;
    integer i;

    initial begin
        $dumpfile("waves/mux4to1_32bit.vcd");
        $dumpvars(0, tb_mux4to1_32bit);

        // do not test all cases, that's far too many
        // test case 1
        for (i = 0; i < 2; i = i + 1) begin
            a = 32'h00000000;
            b = 32'hFFFFFFFF;
            c = 32'hAAAAAAAA;
            d = 32'h55555555;
            sel = i;
            #10;

            expected = (sel == 2'b00) ? a :
                    (sel == 2'b01) ? b :
                    (sel == 2'b10) ? c :
                    d;

            if (out !== expected) begin
                $display("ERROR: a = %h, b = %h, c = %h, d = %h | sel = %h | out = %h, expected = %h", a, b, c, d, sel, out, expected);
                error_count = error_count + 1;
            end
        end

        i = 0;

        // test case 2
        for (i = 0; i < 2; i = i + 1) begin
            a = 32'h12345678;
            b = 32'h87654321;
            c = 32'hDEADBEEF;
            d = 32'hCAFEBABE;
            sel = i;
            #10;

            expected = (sel == 2'b00) ? a :
                    (sel == 2'b01) ? b :
                    (sel == 2'b10) ? c :
                    d;

            if (out !== expected) begin
                $display("ERROR: a = %h, b = %h, c = %h, d = %h | sel = %h | out = %h, expected = %h", a, b, c, d, sel, out, expected);
                error_count = error_count + 1;
            end
        end

        i = 0;

        // test case 3
        for (i = 0; i < 2; i = i + 1) begin
            a = 32'h00000001;
            b = 32'h80000000;
            c = 32'h00008000;
            d = 32'h00010000;
            sel = i;
            #10;

            expected = (sel == 2'b00) ? a :
                    (sel == 2'b01) ? b :
                    (sel == 2'b10) ? c :
                    d;

            if (out !== expected) begin
                $display("ERROR: a = %h, b = %h, c = %h, d = %h | sel = %h | out = %h, expected = %h", a, b, c, d, sel, out, expected);
                error_count = error_count + 1;
            end
        end

        i = 0;

        // test case 4
        for (i = 0; i < 2; i = i + 1) begin
            a = 32'h00000005;
            b = 32'h0000000A;
            c = 32'h0000000F;
            d = 32'h00000010;
            sel = i;
            #10;

            expected = (sel == 2'b00) ? a :
                    (sel == 2'b01) ? b :
                    (sel == 2'b10) ? c :
                    d;

            if (out !== expected) begin
                $display("ERROR: a = %h, b = %h, c = %h, d = %h | sel = %h | out = %h, expected = %h", a, b, c, d, sel, out, expected);
                error_count = error_count + 1;
            end
        end

        i = 0;

        // test case 5
        for (i = 0; i < 2; i = i + 1) begin
            a = 32'h000000FF;
            b = 32'h0000FF00;
            c = 32'h00FF0000;
            d = 32'hFF000000;
            sel = i;
            #10;

            expected = (sel == 2'b00) ? a :
                    (sel == 2'b01) ? b :
                    (sel == 2'b10) ? c :
                    d;

            if (out !== expected) begin
                $display("ERROR: a = %h, b = %h, c = %h, d = %h | sel = %h | out = %h, expected = %h", a, b, c, d, sel, out, expected);
                error_count = error_count + 1;
            end
        end

        $display("ERROR COUNT: %0d", error_count);

        if (error_count == 0)
            $display("TESTBENCH PASSED");

        $finish;
    end
endmodule

waves/mux4to1_32bit.vcd
$date
	Tue Sep 01 22:42:49 2026
$end
$version
	Icarus Verilog
$end
$timescale
	1s
$end
$scope module tb_mux4to1_32bit $end
$var wire 32 ! out [31:0] $end
$var reg 32 " a [31:0] $end
$var reg 32 # b [31:0] $end
$var reg 32 $ c [31:0] $end
$var reg 32 % d [31:0] $end
$var reg 32 & expected [31:0] $end
$var reg 2 ' sel [1:0] $end
$var integer 32 ( error_count [31:0] $end
$var integer 32 ) i [31:0] $end
$scope module uut $end
$var wire 32 * a [31:0] $end
$var wire 32 + b [31:0] $end
$var wire 32 , c [31:0] $end
$var wire 32 - d [31:0] $end
$var wire 2 . sel [1:0] $end
$var wire 32 / out [31:0] $end
$upscope $end
$upscope $end
$enddefinitions $end
$comment Show the parameter values. $end
$dumpall
$end
#0
$dumpvars
b0 /
b0 .
b1010101010101010101010101010101 -
b10101010101010101010101010101010 ,
b11111111111111111111111111111111 +
b0 *
b0 )
b0 (
b0 '
bx &
b1010101010101010101010101010101 %
b10101010101010101010101010101010 $
b11111111111111111111111111111111 #
b0 "
b0 !
$end
#10
b11111111111111111111111111111111 !
b11111111111111111111111111111111 /
b1 '
b1 .
b1 )
b0 &
#20
b10010001101000101011001111000 !
b10010001101000101011001111000 /
b0 '
b0 .
b11001010111111101011101010111110 %
b11001010111111101011101010111110 -
b11011110101011011011111011101111 $
b11011110101011011011111011101111 ,
b10000111011001010100001100100001 #
b10000111011001010100001100100001 +
b10010001101000101011001111000 "
b10010001101000101011001111000 *
b0 )
b11111111111111111111111111111111 &
#30
b10000111011001010100001100100001 !
b10000111011001010100001100100001 /
b1 '
b1 .
b1 )
b10010001101000101011001111000 &
#40
b1 !
b1 /
b0 '
b0 .
b10000000000000000 %
b10000000000000000 -
b1000000000000000 $
b1000000000000000 ,
b10000000000000000000000000000000 #
b10000000000000000000000000000000 +
b1 "
b1 *
b0 )
b10000111011001010100001100100001 &
#50
b10000000000000000000000000000000 !
b10000000000000000000000000000000 /
b1 '
b1 .
b1 )
b1 &
#60
b101 !
b101 /
b0 '
b0 .
b10000 %
b10000 -
b1111 $
b1111 ,
b1010 #
b1010 +
b101 "
b101 *
b0 )
b10000000000000000000000000000000 &
#70
b1010 !
b1010 /
b1 '
b1 .
b1 )
b101 &
#80
b11111111 !
b11111111 /
b0 '
b0 .
b11111111000000000000000000000000 %
b11111111000000000000000000000000 -
b111111110000000000000000 $
b111111110000000000000000 ,
b1111111100000000 #
b1111111100000000 +
b11111111 "
b11111111 *
b0 )
b1010 &
#90
b1111111100000000 !
b1111111100000000 /
b1 '
b1 .
b1 )
b11111111 &
#100
b10 )
b1111111100000000 &
